better_cookiecutter/__init__.py
better_cookiecutter-0.0.1.dist-info/LICENSE
better_cookiecutter-0.0.1.dist-info/WHEEL
better_cookiecutter-0.0.1.dist-info/METADATA
better_cookiecutter-0.0.1.dist-info/RECORD
